lammps_step/__init__.py
lammps_step/__main__.py
lammps_step/_version.py
lammps_step/custom.py
lammps_step/custom_parameters.py
lammps_step/custom_step.py
lammps_step/energy.py
lammps_step/energy_parameters.py
lammps_step/energy_step.py
lammps_step/heat_flux.py
lammps_step/heat_flux_parameters.py
lammps_step/heat_flux_step.py
lammps_step/initialization.py
lammps_step/initialization_parameters.py
lammps_step/initialization_step.py
lammps_step/installer.py
lammps_step/lammps.py
lammps_step/lammps_step.py
lammps_step/lammps_units.py
lammps_step/metadata.py
lammps_step/minimization.py
lammps_step/minimization_parameters.py
lammps_step/minimization_step.py
lammps_step/npt.py
lammps_step/npt_parameters.py
lammps_step/npt_step.py
lammps_step/nve.py
lammps_step/nve_parameters.py
lammps_step/nve_step.py
lammps_step/nvt.py
lammps_step/nvt_parameters.py
lammps_step/nvt_step.py
lammps_step/tk_custom.py
lammps_step/tk_energy.py
lammps_step/tk_heat_flux.py
lammps_step/tk_initialization.py
lammps_step/tk_lammps.py
lammps_step/tk_minimization.py
lammps_step/tk_npt.py
lammps_step/tk_nve.py
lammps_step/tk_nvt.py
lammps_step/tk_velocities.py
lammps_step/velocities.py
lammps_step/velocities_parameters.py
lammps_step/velocities_step.py
lammps_step/data/configuration.txt
lammps_step/data/element_energies.csv
lammps_step/data/lammps.ini
lammps_step/data/properties.csv
lammps_step/data/references.bib
lammps_step/data/seamm-lammps.yml
lammps_step-2026.1.8.dist-info/licenses/AUTHORS.rst
lammps_step-2026.1.8.dist-info/licenses/LICENSE
lammps_step-2026.1.8.dist-info/METADATA
lammps_step-2026.1.8.dist-info/WHEEL
lammps_step-2026.1.8.dist-info/entry_points.txt
lammps_step-2026.1.8.dist-info/top_level.txt
lammps_step-2026.1.8.dist-info/zip-safe
lammps_step-2026.1.8.dist-info/RECORD
