Metadata-Version: 2.4
Name: lammps_step
Version: 2026.1.8
Summary: A SEAMM plug-in for LAMMPS, a forcefield-based molecular dynamics code.
Home-page: https://github.com/molssi-seamm/lammps_step
Author: MolSSI @ Virginia Tech
Author-email: seamm@molssi.org
License: BSD-3-Clause
Keywords: SEAMM,plug-in,flowchart,forcefield,EAM,OpenKIM,molecular dynamics,atomistic,MD
Platform: Linux
Platform: Mac OS-X
Platform: Unix
Platform: Windows
Classifier: Development Status :: 5 - Production/Stable
Classifier: Intended Audience :: Science/Research
Classifier: License :: OSI Approved :: BSD License
Classifier: Natural Language :: English
Classifier: Programming Language :: Python :: 3 :: Only
Classifier: Programming Language :: Python :: 3.8
Classifier: Programming Language :: Python :: 3.9
License-File: LICENSE
License-File: AUTHORS.rst
Requires-Dist: molsystem
Requires-Dist: numpy
Requires-Dist: pandas
Requires-Dist: Pmw
Requires-Dist: py-cpuinfo
Requires-Dist: scipy
Requires-Dist: pymbar>=4.0
Requires-Dist: seamm
Requires-Dist: seamm-exec
Requires-Dist: seamm-ff-util
Requires-Dist: statsmodels
Requires-Dist: tabulate
Dynamic: author
Dynamic: author-email
Dynamic: classifier
Dynamic: description
Dynamic: description-content-type
Dynamic: home-page
Dynamic: keywords
Dynamic: license
Dynamic: license-file
Dynamic: platform
Dynamic: requires-dist
Dynamic: summary
